README.md
setup.py
faster_coco_eval/__init__.py
faster_coco_eval/setup.py
faster_coco_eval/faster_coco_eval/__init__.py
faster_coco_eval/faster_coco_eval/coco.py
faster_coco_eval/faster_coco_eval/cocoeval.py
faster_coco_eval/faster_coco_eval/curves.py
faster_coco_eval/faster_coco_eval/error_calc.py
faster_coco_eval/faster_coco_eval/faster_eval_api.py
faster_coco_eval/faster_coco_eval/mask.py
lvt_eval/__init__.py
lvt_eval.egg-info/PKG-INFO
lvt_eval.egg-info/SOURCES.txt
lvt_eval.egg-info/dependency_links.txt
lvt_eval.egg-info/requires.txt
lvt_eval.egg-info/top_level.txt
lvt_eval/evaluation/__init__.py
lvt_eval/evaluation/coco_json_eval.py
lvt_eval/evaluation/faster_coco_json_eval.py
lvt_eval/evaluation/from_studio_json_eval.py
lvt_eval/tools/__init__.py
lvt_eval/tools/ap_per_class.py
lvt_eval/tools/cal_new_ap.py
lvt_eval/tools/cal_precision_and_recall.py
lvt_eval/tools/cal_pred_error.py
lvt_eval/tools/coco_error_analyze.py
lvt_eval/utils/__init__.py
lvt_eval/utils/boxes.py
lvt_eval/utils/check_predictions.py
lvt_eval/utils/draw_boxes.py
lvt_eval/utils/draw_pr_curve.py
lvt_eval/utils/functions.py
lvt_eval/utils/general.py
lvt_eval/utils/get_classes_and_imgs.py
lvt_eval/utils/merge_bbox.py
lvt_eval/utils/read_gt_img.py
lvt_eval/utils/save_excel.py
lvt_eval/utils/sorted_score.py