Metadata-Version: 2.1
Name: lvt-eval
Version: 0.0.2
Summary: lvt evaluation of image object detrction and image classification.
Home-page: 
Author: KeleiJiang,JiajiaLiao
Author-email: 18852088031@163.com
License: MIT
Classifier: License :: OSI Approved :: MIT License
Classifier: Programming Language :: Python
Classifier: Programming Language :: Python :: 3
Classifier: Programming Language :: Python :: 3.8
Classifier: Programming Language :: Python :: Implementation :: CPython
Classifier: Programming Language :: Python :: Implementation :: PyPy
Requires-Python: >=3.8
